{
    "$schema": "https://schema.management.azure.com/schemas/2019-04-01/deploymentParameters.json#",
    "contentVersion": "1.0.0.0",
    "parameters": {
        "projectName": {
            "value": "ProjectName"
        },
        "adminUsername": {
            "value": "azureuser"
        },
        "adminPublicKey": {
            "value": "SSH-PUB-KEY"
        },
        "location": {
            "value": "East US"
        },
        "vmSize": {
            "value": "Standard_B1s"
        },
        "ipAddress": {
            "value": "*"
        },
        "webVmSize": {
            "value": "Standard_B2s"
        }
    }
}